switter/__init__.py
switter/client.py
switter-0.1.0.dist-info/WHEEL
switter-0.1.0.dist-info/METADATA
switter-0.1.0.dist-info/RECORD
